{
  "data": {
    "grading_schema": {
      "label": "Graded",
      "value": "graded"
    },
    "study_level": {},
    "quota_enrolment_requirements": "",
    "exclusions": "",
    "level": {
      "value": "4000"
    },
    "uac_code": "",
    "special_requirements": "",
    "special_unit_type": [
      {
        "label": "Undergraduate",
        "value": "undergrad"
      }
    ],
    "version_status": {
      "label": "Approved",
      "value": "Active"
    },
    "special_topic": false,
    "asced_broad": {
      "value": ""
    },
    "placement_proportion": {
      "label": "No",
      "value": "no"
    },
    "unit_description": [],
    "unit_learning_outcomes": [
      {
        "description": "Understand contemporary approaches to teaching and learning, especially as they relate to Society and Culture.",
        "code": "ULO3"
      },
      {
        "description": "Appreciate the importance of placing the Society and Culture curriculum within a contemporary context and the capacity to implement learning experiences that use a variety of contemporary resources to promote cross-disciplinary conceptual understanding.",
        "code": "ULO6"
      },
      {
        "description": "Plan and implement learning experiences that emphasise a social inquiry approach to learning.",
        "code": "ULO2"
      },
      {
        "description": "Recognise that the social and cultural diversity of students is a valuable educational resource in the context of the Society and Culture classroom.",
        "code": "ULO4"
      },
      {
        "description": "Plan learning experiences that cater for the diversity of learners within the Society and Culture classroom.",
        "code": "ULO8"
      },
      {
        "description": "Understand the assessment and reporting requirements of Society and Culture, especially as they relate to management and monitoring of students' Personal Interest Projects.",
        "code": "ULO7"
      },
      {
        "description": "Have a working knowledge and understanding of the structure, content and philosophy of the Years 11-12 Society and Culture Syllabus.",
        "code": "ULO1"
      },
      {
        "description": "Build student rapport and foster a supporting learning environment in a subject area highly dependent on discussion and the exchange of social and cultural perspectives and knowledge.",
        "code": "ULO5"
      }
    ],
    "non_scheduled_learning_activities": [
      {
        "description": "Workshop preparation may include completing set readings, conducting research, or, compiling resources",
        "activity": {
          "label": "Class Preparation",
          "value": "class_preparation"
        },
        "offerings": ""
      }
    ],
    "enrolment_rules": [
      {
        "description": "TEP441, TEP440",
        "type": {
          "label": "NCCW (pre-2020 units)",
          "value": "nccw"
        }
      },
      {
        "description": "",
        "type": {
          "label": "Co-requisite",
          "value": "corequisite"
        }
      },
      {
        "description": "(EDTE410 or EDTE4100)",
        "type": {
          "label": "Pre-requisite",
          "value": "prerequisite"
        }
      }
    ],
    "assessments": [
      {
        "assessment_title": "Development and rationale for the personal Interest Project (PIP)",
        "type": {
          "label": "Project",
          "value": "project"
        },
        "weight": "50",
        "description": "Students will develop a proposal for a Personal Interest Project. The proposal includes a Rationale; Research Methods; Justification; and, an Annotated Bibliography (2000 words)",
        "applies_to_all_offerings": "No",
        "hurdle_task": "No",
        "offerings": "",
        "individual": {
          "label": "",
          "value": ""
        }
      },
      {
        "assessment_title": "Supporting Student’s Development of their PIP",
        "type": {
          "label": "Project",
          "value": "project"
        },
        "weight": "50",
        "description": "This assessment consists of TWO parts related to scaffolding student&#39;s development of the PIP. Part 1 covers Focus Question Development for sample students. Part 2 is a pedagogical reflection drawing on recent pedagogical and other scholarly literature. (2000 words)",
        "applies_to_all_offerings": "No",
        "hurdle_task": "No",
        "offerings": "",
        "individual": {
          "label": "",
          "value": ""
        }
      }
    ],
    "requisites": [],
    "unit_offering": [
      {
        "publish": "true",
        "name": "EDTE4400-unit_teaching_period-Weekday-subject",
        "display_name": "Session 2-Weekday-North Ryde",
        "teaching_period": {
          "value": "Session 2"
        },
        "attendance_mode": {
          "value": "Weekday attendance"
        },
        "quota_number": "",
        "study_level": {},
        "academic_item": {
          "value": "EDTE4400"
        }
      },
      {
        "publish": "true",
        "name": "EDTE4400-unit_teaching_period-Special",
        "display_name": "Session 2-Special",
        "teaching_period": {
          "value": "Session 2"
        },
        "attendance_mode": {
          "value": "Special circumstances"
        },
        "quota_number": "",
        "study_level": {},
        "academic_item": {
          "value": "EDTE4400"
        }
      }
    ],
    "unit_offering_text": "Session 2, Weekday attendance, North Ryde<br />Session 2, Special circumstances<br />",
    "subject_search_title": "EDTE4400 - Society and Culture in the Secondary School I",
    "status": {
      "label": "Approved",
      "value": "Active"
    },
    "academic_org": {
      "value": "Macquarie School of Education"
    },
    "school": {
      "value": "Faculty of Arts"
    },
    "credit_points": "10",
    "type": {
      "label": "",
      "value": "non_pace"
    },
    "description": "This unit is designed for students who plan to teach Society and Culture for years 11 and 12 but whose major teaching subject is in another area, such as Geography or History. The unit explores the aims, content and instructional demands of the NESA Society and Culture syllabus documents for Stage 6, and assists students to design innovative, student-centered units of work and to identify or develop appropriate teaching resources.",
    "search_title": "EDTE4400 - Society and Culture in the Secondary School I",
    "code": "EDTE4400",
    "title": "Society and Culture in the Secondary School I",
    "content_type": "Unit",
    "credit_points_header": "10 credit points"
  },
  "creditPoints": 10,
  "description": "This unit is designed for students who plan to teach Society and Culture for years 11 and 12 but whose major teaching subject is in another area, such as Geography or History. The unit explores the aims, content and instructional demands of the NESA Society and Culture syllabus documents for Stage 6, and assists students to design innovative, student-centered units of work and to identify or develop appropriate teaching resources.",
  "level": "4000",
  "publishedInHandbook": 1,
  "levelDisplay": "Unit",
  "effectiveDate": "2021-01-01T00:00:00",
  "status": "Active",
  "modDate": "2020-11-28T10:45:13.667",
  "code": "EDTE4400",
  "title": "Society and Culture in the Secondary School I",
  "implementationYear": "2021"
}