{
  "data": {
    "grading_schema": {
      "label": "Graded",
      "value": "graded"
    },
    "study_level": {},
    "quota_enrolment_requirements": "",
    "exclusions": "",
    "level": {
      "value": "3000"
    },
    "uac_code": "",
    "special_requirements": "",
    "special_unit_type": [
      {
        "label": "Undergraduate",
        "value": "undergrad"
      }
    ],
    "version_status": {
      "label": "Approved",
      "value": "Active"
    },
    "special_topic": false,
    "asced_broad": {
      "value": ""
    },
    "placement_proportion": {
      "label": "Yes",
      "value": "yes"
    },
    "unit_description": [],
    "unit_learning_outcomes": [
      {
        "description": "Demonstrate networking skills and capabilities that will assist with either moving into the workforce or further study.",
        "code": "ULO5"
      },
      {
        "description": "Articulate the goals and results of a project using different forms of communication.",
        "code": "ULO3"
      },
      {
        "description": "Apply techniques of project planning and time management, demonstrating the capacity to meet deadlines agreed upon with the partner.",
        "code": "ULO4"
      },
      {
        "description": "Work effectively and ethically in a multifaceted scientific environment.",
        "code": "ULO6"
      },
      {
        "description": "Apply problem-solving skills in a real-world context using discipline-specific knowledge and skills from throughout the degree.",
        "code": "ULO1"
      },
      {
        "description": "Employ the tools, methodologies, language and conventions of their major to develop and test new ideas.",
        "code": "ULO2"
      }
    ],
    "non_scheduled_learning_activities": [],
    "enrolment_rules": [
      {
        "description": "ASTR310, PHTN310, PHYS311",
        "type": {
          "label": "NCCW (pre-2020 units)",
          "value": "nccw"
        }
      },
      {
        "description": "PHYS301 or PHYS3010",
        "type": {
          "label": "Pre-requisite",
          "value": "prerequisite"
        }
      }
    ],
    "assessments": [
      {
        "assessment_title": "Project documentation",
        "type": {
          "label": "Lab book",
          "value": "lab_book"
        },
        "weight": "15",
        "description": "Documentation is a key component to any project, and acts as an important record of progress during the semester. It will also form an invaluable record when writing the final report, and will allow students to easily pick up where they left off the previous week when returning to the project. The format of this documentation is flexible, and can be tuned to the specific nature of the PACE project. For example, some projects are well suited to keeping a lab book, either physical or electronic, which records all the daily tasks, recorded values, results, plots, thoughts, useful numbers, etc. For other projects, this documentation may come in a different form, e.g. organised notes or minutes from project meetings, GitHub commit records, or progress reports. The documentation is completed during the PACE activity.",
        "applies_to_all_offerings": "No",
        "hurdle_task": "No",
        "offerings": "",
        "individual": {
          "label": "",
          "value": ""
        }
      },
      {
        "assessment_title": "Project Report",
        "type": {
          "label": "Report",
          "value": "report"
        },
        "weight": "25",
        "description": "The students are required to submit a Project Report based on their external placement at the partner organisation. This will generally follow the structure of a scientific report, including introduction to the project topic, description of the data, tools and methods used, presentation of results and analysis, discussion of the findings, and conclusions. Typically, students will work in pairs with the partner. In those cases each student is expected to contribute equally to the project report, and the report must include a statement describing the contributions of each student to the joint project.",
        "applies_to_all_offerings": "No",
        "hurdle_task": "Yes",
        "offerings": "",
        "individual": {
          "label": "Individual and Group",
          "value": "Individual and Group"
        }
      },
      {
        "assessment_title": "Reflective journal",
        "type": {
          "label": "Reflective Writing",
          "value": "reflective_writing"
        },
        "weight": "15",
        "description": "Each student must maintain an individual reflective journal on iLearn consisting of three parts:",
        "applies_to_all_offerings": "No",
        "hurdle_task": "No",
        "offerings": "",
        "individual": {
          "label": "",
          "value": ""
        }
      },
      {
        "assessment_title": "Mentor report",
        "type": {
          "label": "Teacher performance assessment",
          "value": "teacher_perf_assessment"
        },
        "weight": "10",
        "description": "The Macquarie Project Mentor will provide a report on each student&#39;s individual performance during the project. This will be based partly on input from the external project supervisor at the host organisation, as well as exchanges with the Project Mentor during the course of the project. The report will grade performance on topics such as meeting the learning outcomes of the unit, the quality of the student&#39;s contribution to the project and partner organisation, and ability to work as part of the project team. ",
        "applies_to_all_offerings": "No",
        "hurdle_task": "No",
        "offerings": "",
        "individual": {
          "label": "",
          "value": ""
        }
      },
      {
        "assessment_title": "Oral presentation",
        "type": {
          "label": "Presentation",
          "value": "presentation"
        },
        "weight": "10",
        "description": "Each student will give a presentation (with time for questions from the audience) on their work in the final week of session. For students working in pairs, they may present a joint talk, as long as each person presents approximately half of the work. The talk should cover both the research component of the project, and the experience of working at the partner organisation.",
        "applies_to_all_offerings": "No",
        "hurdle_task": "No",
        "offerings": "",
        "individual": {
          "label": "",
          "value": ""
        }
      },
      {
        "assessment_title": "Professional engagement",
        "type": {
          "label": "Portfolio",
          "value": "portfolio"
        },
        "weight": "15",
        "description": "A key role of professional scientists is engaging both with other scientists (through attending seminars) and with the public (through outreach activities). Various opportunities for such activity are available throughout the semester, and may also arise as a result of the placement (e.g. events at the host organisation). To encourage a pro-active approach professional development, students will build a portfolio of such activities that they chose and plan themselves, and will be required to accrue &#39;professional engagement credits&#39; during the course of the unit. Activities may include attendance of research seminars, career networking events, and public outreach activities. Diversity of activities is also required.",
        "applies_to_all_offerings": "No",
        "hurdle_task": "No",
        "offerings": "",
        "individual": {
          "label": "",
          "value": ""
        }
      },
      {
        "assessment_title": "CV and cover letter",
        "type": {
          "label": "Non-academic writing",
          "value": "Non_academic_writing"
        },
        "weight": "10",
        "description": "Students will be required to provide a cover letter and curriculum vitae (CV) in response to a genuine job advert that they have researched and selected. An open application to an organisation chosen by the student is also permitted if a suitable job advert is not available. Students will be expected to use the tools and techniques acquired during the unit to find a suitable job opening or organisation, and provide job-specific application materials in the form of a CV and cover letter.",
        "applies_to_all_offerings": "No",
        "hurdle_task": "No",
        "offerings": "",
        "individual": {
          "label": "",
          "value": ""
        }
      }
    ],
    "requisites": [
      {
        "academic_item_code": "PHYS3810",
        "active": true,
        "description": "",
        "requisite_type": {
          "label": "NCCW (2020 and onwards)",
          "value": "anti_corequisite"
        },
        "academic_item_version_number": "2021.02",
        "containers": [
          {
            "parent_record": {
              "value": "Relationship Builder: PHYS3810"
            },
            "title": "Container 0",
            "parent_connector": {
              "label": "OR",
              "value": "OR"
            },
            "containers": [],
            "relationships": [
              {
                "academic_item": {
                  "value": "Unit: ASTR3810"
                },
                "academic_item_type": {
                  "label": "Unit",
                  "value": "subject"
                },
                "abbr_name": "",
                "academic_item_version_name": "2020.01",
                "academic_item_credit_points": "10",
                "academic_item_name": "Frontiers of Astronomy and Astrophysics",
                "academic_item_code": "ASTR3810",
                "academic_item_url": "/2020/units/ASTR3810"
              }
            ]
          }
        ]
      }
    ],
    "unit_offering": [
      {
        "publish": "true",
        "name": "",
        "display_name": "Session 2-Special",
        "teaching_period": {
          "value": "Session 2"
        },
        "attendance_mode": {
          "value": "Special circumstances"
        },
        "quota_number": "",
        "study_level": {},
        "academic_item": {
          "value": "PHYS3810"
        }
      },
      {
        "publish": "true",
        "name": "",
        "display_name": "Session 2-Weekday-North Ryde",
        "teaching_period": {
          "value": "Session 2"
        },
        "attendance_mode": {
          "value": "Weekday attendance"
        },
        "quota_number": "",
        "study_level": {},
        "academic_item": {
          "value": "PHYS3810"
        }
      }
    ],
    "unit_offering_text": "Session 2, Weekday attendance, North Ryde<br />Session 2, Special circumstances<br />",
    "subject_search_title": "PHYS3810 - Professional Experience in Physics and Astronomy",
    "status": {
      "label": "Approved",
      "value": "Active"
    },
    "academic_org": {
      "value": "Department of Physics and Astronomy "
    },
    "school": {
      "value": "Faculty of Science and Engineering"
    },
    "credit_points": "10",
    "type": {
      "label": "PACE",
      "value": "pace"
    },
    "description": "As the PACE unit for the physics major and the astronomy and astrophysics major, this unit brings together the learning outcomes, and explores how a their major can open doors to a wide range of career paths. The unit begins with a reflective stage in which small groups build their own model of the technical themes and generic skills developed during their degree, and consider how to market these skills to potential employers. Students then develop a professional resume and cover letter targeting actual employment advertisements, and engage in peer review of their documents. The larger part of the unit provides an opportunity to engage with the broader community through a PACE activity of 100 hours duration, conducted in partnership with an industrial, research, or educational institute. Students will apply their skills to a real-world problem of interest to the partner, and report on their experiences, solutions and the project outcomes in a variety of formats including a technical report, high level executive summary, and oral presentation.",
    "search_title": "PHYS3810 - Professional Experience in Physics and Astronomy",
    "code": "PHYS3810",
    "title": "Professional Experience in Physics and Astronomy",
    "content_type": "Unit",
    "credit_points_header": "10 credit points"
  },
  "creditPoints": 10,
  "description": "As the PACE unit for the physics major and the astronomy and astrophysics major, this unit brings together the learning outcomes, and explores how a their major can open doors to a wide range of career paths. The unit begins with a reflective stage in which small groups build their own model of the technical themes and generic skills developed during their degree, and consider how to market these skills to potential employers. Students then develop a professional resume and cover letter targeting actual employment advertisements, and engage in peer review of their documents. The larger part of the unit provides an opportunity to engage with the broader community through a PACE activity of 100 hours duration, conducted in partnership with an industrial, research, or educational institute. Students will apply their skills to a real-world problem of interest to the partner, and report on their experiences, solutions and the project outcomes in a variety of formats including a technical report, high level executive summary, and oral presentation.",
  "level": "3000",
  "publishedInHandbook": 1,
  "levelDisplay": "Unit",
  "effectiveDate": "2021-01-01T00:00:00",
  "status": "Active",
  "modDate": "2020-11-04T12:06:34.311",
  "code": "PHYS3810",
  "title": "Professional Experience in Physics and Astronomy",
  "implementationYear": "2021"
}